wfirma/__init__.py
wfirma/__main__.py
wfirma/models.py
wfirma/py.typed
python_wfirma-0.0.0.dist-info/LICENSE
python_wfirma-0.0.0.dist-info/METADATA
python_wfirma-0.0.0.dist-info/WHEEL
python_wfirma-0.0.0.dist-info/RECORD
