Metadata-Version: 2.1
Name: python-wfirma
Version: 0.0.0
Summary: Python wrapper for wFirma API.
Home-page: https://github.com/gromobrody/python-wfirma
License: MIT
Author: Dominik Kozaczko
Author-email: dominik@kozaczko.info
Requires-Python: >=3.11,<4.0
Classifier: Development Status :: 1 - Planning
Classifier: License :: OSI Approved :: MIT License
Classifier: Programming Language :: Python :: 3
Classifier: Programming Language :: Python :: 3.11
Classifier: Programming Language :: Python :: 3.12
Requires-Dist: anyio[trio] (>=4.3.0,<5.0.0)
Requires-Dist: httpx (>=0.27.0,<0.28.0)
Requires-Dist: pydantic (>=2.7.0,<3.0.0)
Requires-Dist: typer (>=0.12.3,<0.13.0)
Project-URL: Changelog, https://github.com/gromobrody/python-wfirma/releases
Project-URL: Documentation, https://python-wfirma.readthedocs.io
Project-URL: Repository, https://github.com/gromobrody/python-wfirma
